setup.py
setup_local.py
pypro/__init__.py
pypro/head_builder.py
pypro/utils.py
pypro/local/__init__.py
pypro/local/body_builder.py
pypro/local/config.py
pypro/local/cpu_poller.py
pypro/local/example.py
pypro/local/io_poller.py
pypro/local/main.py
pypro/local/mem_poller.py
pypro/local/proc_poller.py
pypro/local/loggers/__init__.py
pypro/local/loggers/csv_file_logger.py
pypro/local/loggers/es_file_logger.py
pypro/local/loggers/es_network_logger.py
pypro/local/loggers/kafka_logger.py
pypro/local/loggers/mysql_logger.py
pypro_local.egg-info/PKG-INFO
pypro_local.egg-info/SOURCES.txt
pypro_local.egg-info/dependency_links.txt
pypro_local.egg-info/requires.txt
pypro_local.egg-info/top_level.txt
pypro_local.egg-info/zip-safe