Metadata-Version: 1.1
Name: pypro-local
Version: 0.5.1
Summary: System resource probes
Home-page: https://github.com/mukatee/pypro
Author: Teemu Kanstren
Author-email: tkanstren@gmail.com
License: MIT
Keywords: monitoring
Platform: UNKNOWN
Classifier: License :: OSI Approved :: MIT License
Classifier: Programming Language :: Python :: 3.4
Classifier: Development Status :: 4 - Beta
Classifier: Topic :: System :: Monitoring
